[{"weeks": [{"a": 13062, "c": 12, "d": 304, "w": 1470528000}, {"a": 549, "c": 16, "d": 3839, "w": 1471132800}, {"a": 0, "c": 0, "d": 0, "w": 1471737600}, {"a": 0, "c": 0, "d": 0, "w": 1472342400}, {"a": 0, "c": 0, "d": 0, "w": 1472947200}, {"a": 0, "c": 0, "d": 0, "w": 1473552000}, {"a": 0, "c": 0, "d": 0, "w": 1474156800}, {"a": 0, "c": 0, "d": 0, "w": 1474761600}, {"a": 0, "c": 0, "d": 0, "w": 1475366400}, {"a": 0, "c": 0, "d": 0, "w": 1475971200}, {"a": 0, "c": 0, "d": 0, "w": 1476576000}, {"a": 0, "c": 0, "d": 0, "w": 1477180800}, {"a": 0, "c": 0, "d": 0, "w": 1477785600}, {"a": 0, "c": 0, "d": 0, "w": 1478390400}, {"a": 0, "c": 0, "d": 0, "w": 1478995200}, {"a": 242, "c": 3, "d": 21, "w": 1479600000}, {"a": 15, "c": 2, "d": 6, "w": 1480204800}, {"a": 0, "c": 0, "d": 0, "w": 1480809600}], "total": 33, "author": {"following_url": "https://api.github.com/users/nihal111/following{/other_user}", "events_url": "https://api.github.com/users/nihal111/events{/privacy}", "organizations_url": "https://api.github.com/users/nihal111/orgs", "url": "https://api.github.com/users/nihal111", "gists_url": "https://api.github.com/users/nihal111/gists{/gist_id}", "html_url": "https://github.com/nihal111", "subscriptions_url": "https://api.github.com/users/nihal111/subscriptions", "avatar_url": "https://avatars.githubusercontent.com/u/13916513?v=3", "repos_url": "https://api.github.com/users/nihal111/repos", "received_events_url": "https://api.github.com/users/nihal111/received_events", "gravatar_id": "", "starred_url": "https://api.github.com/users/nihal111/starred{/owner}{/repo}", "site_admin": false, "login": "nihal111", "type": "User", "id": 13916513, "followers_url": "https://api.github.com/users/nihal111/followers"}}, {"weeks": [{"a": 14287, "c": 15, "d": 142, "w": 1470528000}, {"a": 347, "c": 16, "d": 568, "w": 1471132800}, {"a": 0, "c": 0, "d": 0, "w": 1471737600}, {"a": 0, "c": 0, "d": 0, "w": 1472342400}, {"a": 0, "c": 0, "d": 0, "w": 1472947200}, {"a": 0, "c": 0, "d": 0, "w": 1473552000}, {"a": 0, "c": 0, "d": 0, "w": 1474156800}, {"a": 0, "c": 0, "d": 0, "w": 1474761600}, {"a": 0, "c": 0, "d": 0, "w": 1475366400}, {"a": 0, "c": 0, "d": 0, "w": 1475971200}, {"a": 0, "c": 0, "d": 0, "w": 1476576000}, {"a": 0, "c": 0, "d": 0, "w": 1477180800}, {"a": 0, "c": 0, "d": 0, "w": 1477785600}, {"a": 0, "c": 0, "d": 0, "w": 1478390400}, {"a": 0, "c": 0, "d": 0, "w": 1478995200}, {"a": 186, "c": 7, "d": 62, "w": 1479600000}, {"a": 17, "c": 1, "d": 0, "w": 1480204800}, {"a": 0, "c": 0, "d": 0, "w": 1480809600}], "total": 39, "author": {"following_url": "https://api.github.com/users/arpan98/following{/other_user}", "events_url": "https://api.github.com/users/arpan98/events{/privacy}", "organizations_url": "https://api.github.com/users/arpan98/orgs", "url": "https://api.github.com/users/arpan98", "gists_url": "https://api.github.com/users/arpan98/gists{/gist_id}", "html_url": "https://github.com/arpan98", "subscriptions_url": "https://api.github.com/users/arpan98/subscriptions", "avatar_url": "https://avatars.githubusercontent.com/u/13916525?v=3", "repos_url": "https://api.github.com/users/arpan98/repos", "received_events_url": "https://api.github.com/users/arpan98/received_events", "gravatar_id": "", "starred_url": "https://api.github.com/users/arpan98/starred{/owner}{/repo}", "site_admin": false, "login": "arpan98", "type": "User", "id": 13916525, "followers_url": "https://api.github.com/users/arpan98/followers"}}, {"weeks": [{"a": 349, "c": 12, "d": 307, "w": 1470528000}, {"a": 309, "c": 18, "d": 65, "w": 1471132800}, {"a": 0, "c": 1, "d": 3, "w": 1471737600}, {"a": 23512, "c": 2, "d": 23512, "w": 1472342400}, {"a": 29, "c": 2, "d": 12, "w": 1472947200}, {"a": 0, "c": 0, "d": 0, "w": 1473552000}, {"a": 0, "c": 0, "d": 0, "w": 1474156800}, {"a": 0, "c": 0, "d": 0, "w": 1474761600}, {"a": 0, "c": 0, "d": 0, "w": 1475366400}, {"a": 0, "c": 0, "d": 0, "w": 1475971200}, {"a": 0, "c": 0, "d": 0, "w": 1476576000}, {"a": 0, "c": 0, "d": 0, "w": 1477180800}, {"a": 0, "c": 0, "d": 0, "w": 1477785600}, {"a": 0, "c": 0, "d": 0, "w": 1478390400}, {"a": 0, "c": 0, "d": 0, "w": 1478995200}, {"a": 36243, "c": 25, "d": 35, "w": 1479600000}, {"a": 4, "c": 2, "d": 1, "w": 1480204800}, {"a": 0, "c": 0, "d": 0, "w": 1480809600}], "total": 62, "author": {"following_url": "https://api.github.com/users/CodeMaxx/following{/other_user}", "events_url": "https://api.github.com/users/CodeMaxx/events{/privacy}", "organizations_url": "https://api.github.com/users/CodeMaxx/orgs", "url": "https://api.github.com/users/CodeMaxx", "gists_url": "https://api.github.com/users/CodeMaxx/gists{/gist_id}", "html_url": "https://github.com/CodeMaxx", "subscriptions_url": "https://api.github.com/users/CodeMaxx/subscriptions", "avatar_url": "https://avatars.githubusercontent.com/u/14044709?v=3", "repos_url": "https://api.github.com/users/CodeMaxx/repos", "received_events_url": "https://api.github.com/users/CodeMaxx/received_events", "gravatar_id": "", "starred_url": "https://api.github.com/users/CodeMaxx/starred{/owner}{/repo}", "site_admin": false, "login": "CodeMaxx", "type": "User", "id": 14044709, "followers_url": "https://api.github.com/users/CodeMaxx/followers"}}]